{"title":"Exercise A. Vocabulary","clock":true,"countdown":0,"intro":{"buttons":{"start":"Start"},"content":[]},"activity":{"scenes":[{"block":"scene","name":"SC1","countdown":0,"instructions":{"open":true,"content":[{"block":"group","class":"flex gap-2 items-center","content":[{"block":"audio","class":"","file":"files/i-listen.mp3","wave":false,"autoplay":false,"id":"","name":"vwxe"},{"block":"text","class":"","text":" Listen to the descriptions and drag and drop the phrase that matches the subject","id":"","name":"QlCp"}]}]},"content":[{"block":"group","class":"max-w-xl mx-auto","content":[{"order":false,"class":"flex-wrap gap-2","group":"uno","content":[{"text":"was short","class":"normal-case","id":"Xaqu4WwT","block":"text","name":"WfpO"},{"text":"was eccentric","class":"normal-case","id":"PyiFtpwz","block":"text","name":"M7pv"},{"text":"was very creative","class":"normal-case","id":"NN4sQS2j","block":"text","name":"5Exh"},{"text":"was a writer","class":"normal-case","id":"3tYQfFJ2","block":"text","name":"0BfR"},{"text":"was beautiful","class":"normal-case","id":"gjQZ","block":"text","name":"6vcw"},{"text":"was a British singer","class":"normal-case","id":"33a0OXhZ","block":"text","name":"q98F"}],"positive":"","evaluation":"","showResult":false,"id":"NWWt","block":"dragdrop","name":"Nnjy","attempts":0}],"background":"","name":"4Cs6","hidden":false,"id":""},{"class":"grid grid-cols-3 gap-2 mt-5 mx-20","content":[{"class":"bg-info rounded p-2 text-center text-white text-lg","content":[{"text":"Princess Diana","class":"","id":"KnzH","block":"text","name":"d1iG"},{"file":"files/diana Medium.jpeg","class":"mask mask-squircle my-5","id":"19PR","block":"image","name":"IzC4"},{"order":false,"class":"","group":"uno","content":[],"positive":"6vcw","evaluation":"auto","showResult":false,"id":"B1HF","block":"dragdrop","name":"zk13","attempts":0}],"background":"","id":"Ev8Z","block":"group","name":"uRgJ"},{"class":"bg-info rounded p-2 text-center text-white text-lg","content":[{"text":"Queen Elizabeth II","class":"","id":"KnzHFf92","block":"text","name":"Bv1B"},{"file":"files/queenheight Medium.jpeg","class":"mask mask-squircle my-5","id":"19PRCCZK","block":"image","name":"FhMT"},{"order":false,"class":"","group":"uno","content":[],"positive":"WfpO","evaluation":"auto","showResult":false,"id":"B1HF9U4p","block":"dragdrop","name":"76nj","attempts":0}],"background":"","id":"SKyqHOOa","block":"group","name":"gCb3"},{"class":"bg-info rounded p-2 text-center text-white text-lg","content":[{"text":"John Lennon","class":"","id":"KnzHkIYo","block":"text","name":"6eBX"},{"file":"files/lennon Medium.jpeg","class":"mask mask-squircle my-5","id":"19PRi8a0","block":"image","name":"AmcQ"},{"order":false,"class":"","group":"uno","content":[],"positive":"q98F","evaluation":"auto","showResult":false,"id":"B1HFGJf9","block":"dragdrop","name":"cjVt","attempts":0}],"background":"","id":"b1vvyLW3","block":"group","name":"CT4R"},{"class":"bg-info rounded p-2 text-center text-white text-lg","content":[{"text":"Charles Dickens","class":"","id":"KnzHIYy8","block":"text","name":"5omU"},{"file":"files/dickens Medium.jpeg","class":"mask mask-squircle my-5","id":"19PRLRdO","block":"image","name":"4Zgh"},{"order":false,"class":"","group":"uno","content":[],"positive":"0BfR","evaluation":"auto","showResult":false,"id":"B1HFHjzg","block":"dragdrop","name":"ZUsG","attempts":0}],"background":"","id":"Az1QfUel","block":"group","name":"fVWv"},{"class":"bg-info rounded p-2 text-center text-white text-xl","content":[{"text":"Amy Winehouse","class":"","id":"KnzHAlko","block":"text","name":"bfOY"},{"file":"files/amy Medium.jpeg","class":"mask mask-squircle my-5","id":"19PRxgUb","block":"image","name":"DEWO"},{"order":false,"class":"","group":"uno","content":[],"positive":"M7pv","evaluation":"auto","showResult":false,"id":"B1HFzBAY","block":"dragdrop","name":"lyG9","attempts":0}],"background":"","id":"l2wMzPNg","block":"group","name":"VvJR"},{"class":"bg-info rounded p-2 text-center text-white text-xl","content":[{"text":"Gianni Versace","class":"","id":"KnzHRw05","block":"text","name":"0XEf"},{"file":"files/versace Medium.jpeg","class":"mask mask-squircle my-5","id":"19PRZcSx","block":"image","name":"ug6K"},{"order":false,"class":"","group":"uno","content":[],"positive":"5Exh","evaluation":"auto","showResult":false,"id":"B1HFFkZI","block":"dragdrop","name":"RBAl","attempts":0}],"background":"","id":"c2s2kmRb","block":"group","name":"yL6O"}],"background":"","id":"g2p1","block":"group","name":"gDY3"},{"symbol":"FinalizeGroup"}],"id":""}]},"end":{"buttons":{"restart":false},"content":[{"symbol":"finishedAll"}]},"symbols":{"finishedAll":{"class":"w-full","content":[{"block":"group","class":"bg-slate-100 rounded p-5 text-center w-full","content":[{"block":"text","text":"Congratulations, you finished the activity.","class":"","name":"Congra"}],"background":"","name":"CongraGroup"},{"block":"group","class":"text-center p-5","content":[{"block":"finished","name":"finishedBlock"}],"background":"","name":"finishedGroup"}],"background":"","block":"group"},"FinalizeGroup":{"block":"group","class":"text-center mt-10","content":[{"block":"button","class":"mx-auto","to":"/end","text":"Finalize","name":"FinalizeBTN"}],"background":""}}}