{"title":"Semicontrolled Practice","clock":true,"countdown":0,"attempts":0,"intro":{"buttons":{"start":"Start"},"content":[]},"activity":{"scenes":[{"block":"scene","name":"SC1","countdown":0,"instructions":{"open":true,"content":[{"block":"group","class":"flex gap-2 items-center","content":[{"block":"audio","class":"","file":"files/inst.mp3","wave":false,"autoplay":false,"id":"","name":"PdMZ"},{"block":"text","class":"","text":"Read the sentences and fill the gaps with the correct verb and tense. Add information to personalize your own fiction. Don't forget to use contractions. ","id":"","name":"JogP"}]}]},"content":[{"block":"group","class":"bg-slate-100 rounded p-3 my-2 max-w-3xl mx-auto","content":[{"marker":"","class":"flex justify-center ","content":[{"file":"files/img01.jpg","class":"mask mask-circle w-3/4","id":"jdtu","block":"image","name":"3Kru"}],"background":"","id":"HeEF","block":"group","name":"gOI2"},{"marker":"","class":"grid gap-10 m-5 p-5","content":[{"marker":"","class":"text-xl","content":[{"text":"1.","class":"mr-1 bg-yellow-400 p-1 rounded","id":"Nh7I","block":"text","name":"Z6Ws"},{"text":"She","class":"","id":"4auO","block":"text","name":"6B6U"},{"marker":"","class":"inline-block w-40","content":[{"case":false,"evaluation":"manual","class":"text-center ","positive":"","multiline":false,"placeholder":"-","showResult":false,"id":"ZPLA","block":"textarea","name":"awiH","maxlength":0,"attempts":0}],"background":"","id":"S1Tr","block":"group","name":"tjYD"},{"text":"( write)","class":"","id":"BySykn3t","block":"text","name":"jz7O"},{"marker":"","class":"inline-block w-40","content":[{"case":false,"evaluation":"manual","class":"text-center","positive":"","multiline":false,"placeholder":"-","showResult":false,"id":"ZPLAaqI6","block":"textarea","name":"ijW9","maxlength":0,"attempts":0}],"background":"","id":"XTehdXO1","block":"group","name":"HqVl"},{"text":"by the time she","class":"","id":"8BotE5M6","block":"text","name":"RuuG"},{"marker":"","class":"inline-block w-40","content":[{"case":false,"evaluation":"manual","class":"text-center","positive":"","multiline":false,"placeholder":"-","showResult":false,"id":"ZPLAaqI6fD2L","block":"textarea","name":"R4PS","maxlength":0,"attempts":0}],"background":"","id":"iFjHJacb","block":"group","name":"wilq"},{"text":"(be)","class":"","id":"WrubOVWR","block":"text","name":"j7aH"},{"marker":"","class":"inline-block w-40","content":[{"case":false,"evaluation":"manual","class":"text-center","positive":"","multiline":false,"placeholder":"-","showResult":false,"id":"ZPLAaqI6fD2LrNrk","block":"textarea","name":"0wfD","maxlength":0,"attempts":0}],"background":"","id":"fjcG5UU3","block":"group","name":"dTew"},{"text":".","class":"","id":"Z0j8eUGB","block":"text","name":"CdDf"}],"background":"","id":"PibI","block":"group","name":"5qWf"},{"marker":"","class":"text-xl","content":[{"text":"2.","class":"mr-1 bg-yellow-400 p-1 rounded","id":"Nh7IkaPJ","block":"text","name":"A4NJ"},{"text":"He","class":"","id":"4auOyy76","block":"text","name":"BrmF"},{"marker":"","class":"inline-block w-40","content":[{"case":false,"evaluation":"manual","class":"text-center ","positive":"","multiline":false,"placeholder":"-","showResult":false,"id":"ZPLAF5MF","block":"textarea","name":"tneQ","maxlength":0,"attempts":0}],"background":"","id":"S1Tr0t3y","block":"group","name":"Yhmn"},{"text":"( take)","class":"","id":"BySykn3t0TDj","block":"text","name":"0dzt"},{"marker":"","class":"inline-block w-40","content":[{"case":false,"evaluation":"manual","class":"text-center","positive":"","multiline":false,"placeholder":"-","showResult":false,"id":"ZPLAaqI6VqsX","block":"textarea","name":"49N4","maxlength":0,"attempts":0}],"background":"","id":"XTehdXO18VOQ","block":"group","name":"JERs"},{"text":"when the giant","class":"","id":"8BotE5M696vb","block":"text","name":"AFAP"},{"marker":"","class":"inline-block w-40","content":[{"case":false,"evaluation":"manual","class":"text-center","positive":"","multiline":false,"placeholder":"-","showResult":false,"id":"ZPLAaqI6fD2LWgOY","block":"textarea","name":"dCdl","maxlength":0,"attempts":0}],"background":"","id":"iFjHJacbJYLq","block":"group","name":"2UVX"},{"text":"(wake up).","class":"","id":"WrubOVWRoTk1","block":"text","name":"s30C"}],"background":"","id":"31fIhHu0","block":"group","name":"Sbrt"},{"marker":"","class":"text-xl","content":[{"text":"3.","class":"mr-1 bg-yellow-400 p-1 rounded","id":"Nh7IkaPJv4PM","block":"text","name":"GQqC"},{"text":"The beanstalk","class":"","id":"4auOyy76avVC","block":"text","name":"724m"},{"marker":"","class":"inline-block w-40","content":[{"case":false,"evaluation":"manual","class":"text-center ","positive":"","multiline":false,"placeholder":"-","showResult":false,"id":"ZPLAF5MFMlhs","block":"textarea","name":"QU4q","maxlength":0,"attempts":0}],"background":"","id":"S1Tr0t3ya50F","block":"group","name":"p9Vg"},{"text":"(grow up) before","class":"","id":"BySykn3t0TDjj58F","block":"text","name":"MBmb"},{"marker":"","class":"inline-block w-40","content":[{"case":false,"evaluation":"manual","class":"text-center","positive":"","multiline":false,"placeholder":"-","showResult":false,"id":"ZPLAaqI6VqsXjK36","block":"textarea","name":"3n1y","maxlength":0,"attempts":0}],"background":"","id":"XTehdXO18VOQnQH3","block":"group","name":"lAUc"},{"text":"(be)","class":"","id":"8BotE5M696vbjOGP","block":"text","name":"Dcxi"},{"marker":"","class":"inline-block w-40","content":[{"case":false,"evaluation":"manual","class":"text-center","positive":"","multiline":false,"placeholder":"-","showResult":false,"id":"ZPLAaqI6fD2LWgOY6kZP","block":"textarea","name":"Vpbc","maxlength":0,"attempts":0}],"background":"","id":"iFjHJacbJYLqMiGC","block":"group","name":"TKo1"},{"text":".","class":"","id":"WrubOVWRoTk1dDKj","block":"text","name":"bIci"}],"background":"","id":"cBmbJYyv","block":"group","name":"6mFa"},{"marker":"","class":"text-xl","content":[{"text":"4.","class":"mr-1 bg-yellow-400 p-1 rounded","id":"Nh7IkaPJv4PMZEqU","block":"text","name":"8p4i"},{"text":"She","class":"","id":"4auOyy76avVCWDRW","block":"text","name":"SHVT"},{"marker":"","class":"inline-block w-40","content":[{"case":false,"evaluation":"manual","class":"text-center ","positive":"","multiline":false,"placeholder":"-","showResult":false,"id":"ZPLAF5MFMlhsy1uy","block":"textarea","name":"fWrj","maxlength":0,"attempts":0}],"background":"","id":"S1Tr0t3ya50FzXA9","block":"group","name":"UiZI"},{"text":"(freeze)","class":"","id":"BySykn3t0TDjj58FZaOL","block":"text","name":"LMvu"},{"marker":"","class":"inline-block w-40","content":[{"case":false,"evaluation":"manual","class":"text-center","positive":"","multiline":false,"placeholder":"-","showResult":false,"id":"ZPLAaqI6VqsXjK369A1V","block":"textarea","name":"lq9T","maxlength":0,"attempts":0}],"background":"","id":"XTehdXO18VOQnQH3RdG0","block":"group","name":"TsYY"},{"text":"when she","class":"","id":"8BotE5M696vbjOGP0l8B","block":"text","name":"8oyh"},{"marker":"","class":"inline-block w-40","content":[{"case":false,"evaluation":"manual","class":"text-center","positive":"","multiline":false,"placeholder":"-","showResult":false,"id":"ZPLAaqI6fD2LWgOY6kZP2f38","block":"textarea","name":"0Lji","maxlength":0,"attempts":0}],"background":"","id":"iFjHJacbJYLqMiGCPwMG","block":"group","name":"gIBe"},{"text":"(try) to escape.","class":"","id":"WrubOVWRoTk1dDKjdRqY","block":"text","name":"fEnN"}],"background":"","id":"lRKLJLIh","block":"group","name":"DqFn"},{"marker":"","class":"text-xl","content":[{"text":"5.","class":"mr-1 bg-yellow-400 p-1 rounded","id":"Nh7IkaPJv4PMZEqU2drp","block":"text","name":"U3Lv"},{"text":"He","class":"","id":"4auOyy76avVCWDRWajQk","block":"text","name":"XlF7"},{"marker":"","class":"inline-block w-40","content":[{"case":false,"evaluation":"manual","class":"text-center ","positive":"","multiline":false,"placeholder":"-","showResult":false,"id":"ZPLAF5MFMlhsy1uyivmf","block":"textarea","name":"QJYO","maxlength":0,"attempts":0}],"background":"","id":"S1Tr0t3ya50FzXA9Xhdy","block":"group","name":"da5z"},{"text":"(catch)","class":"","id":"BySykn3t0TDjj58FZaOLHJbb","block":"text","name":"DafJ"},{"marker":"","class":"inline-block w-40","content":[{"case":false,"evaluation":"manual","class":"text-center","positive":"","multiline":false,"placeholder":"-","showResult":false,"id":"ZPLAaqI6VqsXjK369A1VsjPV","block":"textarea","name":"Mq6T","maxlength":0,"attempts":0}],"background":"","id":"XTehdXO18VOQnQH3RdG0bMpj","block":"group","name":"llH4"},{"text":"by the time I","class":"","id":"8BotE5M696vbjOGP0l8Bxpo6","block":"text","name":"OOSY"},{"marker":"","class":"inline-block w-40","content":[{"case":false,"evaluation":"manual","class":"text-center","positive":"","multiline":false,"placeholder":"-","showResult":false,"id":"ZPLAaqI6fD2LWgOY6kZP2f38blDb","block":"textarea","name":"y0UD","maxlength":0,"attempts":0}],"background":"","id":"iFjHJacbJYLqMiGCPwMGREXV","block":"group","name":"tyNy"},{"text":"(get)","class":"","id":"WrubOVWRoTk1dDKjdRqYXmmF","block":"text","name":"Hznt"},{"marker":"","class":"inline-block w-40","content":[{"case":false,"evaluation":"manual","class":"text-center","positive":"","multiline":false,"placeholder":"-","showResult":false,"id":"ZPLAaqI6fD2LWgOY6kZP2f38blDbhcSe","block":"textarea","name":"3PxT","maxlength":0,"attempts":0}],"background":"","id":"cVi1YKdb","block":"group","name":"LQBg"},{"text":".","class":"","id":"rJM3G7BA","block":"text","name":"6CqP"}],"background":"","id":"rNSZZHAu","block":"group","name":"yXs5"},{"marker":"","class":"text-xl","content":[{"text":"6.","class":"mr-1 bg-yellow-400 p-1 rounded","id":"Nh7IkaPJv4PMZEqU2drpCZQt","block":"text","name":"rdvL"},{"text":"The princess","class":"","id":"4auOyy76avVCWDRWajQkzZwP","block":"text","name":"lVwA"},{"marker":"","class":"inline-block w-40","content":[{"case":false,"evaluation":"manual","class":"text-center ","positive":"","multiline":false,"placeholder":"-","showResult":false,"id":"ZPLAF5MFMlhsy1uyivmfaaN4","block":"textarea","name":"Gch8","maxlength":0,"attempts":0}],"background":"","id":"S1Tr0t3ya50FzXA9XhdyyPmh","block":"group","name":"jTvo"},{"text":"( send) the message when the pirate","class":"","id":"BySykn3t0TDjj58FZaOLHJbbUYzD","block":"text","name":"IjXi"},{"marker":"","class":"inline-block w-40","content":[{"case":false,"evaluation":"manual","class":"text-center","positive":"","multiline":false,"placeholder":"-","showResult":false,"id":"ZPLAaqI6VqsXjK369A1VsjPVyI15","block":"textarea","name":"gPLA","maxlength":0,"attempts":0}],"background":"","id":"XTehdXO18VOQnQH3RdG0bMpjYQce","block":"group","name":"LgvV"},{"text":"(arise) from the ocean.","class":"","id":"8BotE5M696vbjOGP0l8Bxpo6Ex0t","block":"text","name":"LN9O"}],"background":"","id":"37aPKysI","block":"group","name":"ot8Z"},{"marker":"","class":"text-xl","content":[{"text":"7.","class":"mr-1 bg-yellow-400 p-1 rounded","id":"Nh7IkaPJv4PMZEqU2drpCZQty3rW","block":"text","name":"7ZMx"},{"text":"The robot","class":"","id":"4auOyy76avVCWDRWajQkzZwPABOA","block":"text","name":"N8wr"},{"marker":"","class":"inline-block w-40","content":[{"case":false,"evaluation":"manual","class":"text-center ","positive":"","multiline":false,"placeholder":"-","showResult":false,"id":"ZPLAF5MFMlhsy1uyivmfaaN4YiNR","block":"textarea","name":"uov7","maxlength":0,"attempts":0}],"background":"","id":"S1Tr0t3ya50FzXA9XhdyyPmhPZDn","block":"group","name":"n2BA"},{"text":"(bite) the metal door so we","class":"","id":"BySykn3t0TDjj58FZaOLHJbbUYzDLWGG","block":"text","name":"Udwf"},{"marker":"","class":"inline-block w-40","content":[{"case":false,"evaluation":"manual","class":"text-center","positive":"","multiline":false,"placeholder":"-","showResult":false,"id":"ZPLAaqI6VqsXjK369A1VsjPVyI15TcdZ","block":"textarea","name":"svkG","maxlength":0,"attempts":0}],"background":"","id":"XTehdXO18VOQnQH3RdG0bMpjYQceTbSk","block":"group","name":"cPYw"},{"text":"(run) away.","class":"","id":"8BotE5M696vbjOGP0l8Bxpo6Ex0tNxBW","block":"text","name":"nDqj"}],"background":"","id":"w06FeCF1","block":"group","name":"EFmV"},{"marker":"","class":"text-xl","content":[{"text":"8.","class":"mr-1 bg-yellow-400 p-1 rounded","id":"Nh7IkaPJv4PMZEqU2drpCZQty3rWCy39","block":"text","name":"Bq9r"},{"text":"The Dragon","class":"","id":"4auOyy76avVCWDRWajQkzZwPABOAaqXK","block":"text","name":"Xsh8"},{"marker":"","class":"inline-block w-40","content":[{"case":false,"evaluation":"manual","class":"text-center ","positive":"","multiline":false,"placeholder":"-","showResult":false,"id":"ZPLAF5MFMlhsy1uyivmfaaN4YiNRDSRU","block":"textarea","name":"uhr0","maxlength":0,"attempts":0}],"background":"","id":"S1Tr0t3ya50FzXA9XhdyyPmhPZDnf3ky","block":"group","name":"vPHW"},{"text":"(blow) the entire castle by the time the prince","class":"","id":"BySykn3t0TDjj58FZaOLHJbbUYzDLWGGWcSv","block":"text","name":"2kNh"},{"marker":"","class":"inline-block w-40","content":[{"case":false,"evaluation":"manual","class":"text-center","positive":"","multiline":false,"placeholder":"-","showResult":false,"id":"ZPLAaqI6VqsXjK369A1VsjPVyI15TcdZcjRg","block":"textarea","name":"JuDX","maxlength":0,"attempts":0}],"background":"","id":"XTehdXO18VOQnQH3RdG0bMpjYQceTbSkI7Iu","block":"group","name":"kfrR"},{"text":"(arrive) with his army.","class":"","id":"8BotE5M696vbjOGP0l8Bxpo6Ex0tNxBWUzJ5","block":"text","name":"ou5Q"}],"background":"","id":"xwAnQafg","block":"group","name":"3RbX"},{"marker":"","class":"text-xl","content":[{"text":"9.","class":"mr-1 bg-yellow-400 p-1 rounded","id":"Nh7IkaPJv4PMZEqU2drpCZQty3rWCy39lfD2","block":"text","name":"ExBH"},{"text":"The knights","class":"","id":"4auOyy76avVCWDRWajQkzZwPABOAaqXKAUPG","block":"text","name":"vTAX"},{"marker":"","class":"inline-block w-40","content":[{"case":false,"evaluation":"manual","class":"text-center ","positive":"","multiline":false,"placeholder":"-","showResult":false,"id":"ZPLAF5MFMlhsy1uyivmfaaN4YiNRDSRUsbC5","block":"textarea","name":"rsDM","maxlength":0,"attempts":0}],"background":"","id":"S1Tr0t3ya50FzXA9XhdyyPmhPZDnf3kyPkZu","block":"group","name":"fDEf"},{"text":"(feed) the horses before they","class":"","id":"BySykn3t0TDjj58FZaOLHJbbUYzDLWGGWcSvjX3i","block":"text","name":"Coeq"},{"marker":"","class":"inline-block w-40","content":[{"case":false,"evaluation":"manual","class":"text-center","positive":"","multiline":false,"placeholder":"-","showResult":false,"id":"ZPLAaqI6VqsXjK369A1VsjPVyI15TcdZcjRg5XOo","block":"textarea","name":"q9Go","maxlength":0,"attempts":0}],"background":"","id":"XTehdXO18VOQnQH3RdG0bMpjYQceTbSkI7IuJw1I","block":"group","name":"v7nQ"},{"text":"(leave) the lodge.","class":"","id":"8BotE5M696vbjOGP0l8Bxpo6Ex0tNxBWUzJ5dWsM","block":"text","name":"ckOg"}],"background":"","id":"bPEwNwON","block":"group","name":"8wgx"},{"marker":"","class":"text-xl","content":[{"text":"10.","class":"mr-1 bg-yellow-400 p-1 rounded","id":"Nh7IkaPJv4PMZEqU2drpCZQty3rWCy39lfD2RGaE","block":"text","name":"DFmP"},{"text":"The monks","class":"","id":"4auOyy76avVCWDRWajQkzZwPABOAaqXKAUPGFnBm","block":"text","name":"lPeJ"},{"marker":"","class":"inline-block w-40","content":[{"case":false,"evaluation":"manual","class":"text-center ","positive":"","multiline":false,"placeholder":"-","showResult":false,"id":"ZPLAF5MFMlhsy1uyivmfaaN4YiNRDSRUsbC5ZL2n","block":"textarea","name":"GeuE","maxlength":0,"attempts":0}],"background":"","id":"S1Tr0t3ya50FzXA9XhdyyPmhPZDnf3kyPkZuHXb2","block":"group","name":"dN4M"},{"text":"(forbid) the contact with aliens before the robots","class":"","id":"BySykn3t0TDjj58FZaOLHJbbUYzDLWGGWcSvjX3isuXs","block":"text","name":"NZCB"},{"marker":"","class":"inline-block w-40","content":[{"case":false,"evaluation":"manual","class":"text-center","positive":"","multiline":false,"placeholder":"-","showResult":false,"id":"ZPLAaqI6VqsXjK369A1VsjPVyI15TcdZcjRg5XOoRAN9","block":"textarea","name":"91Nu","maxlength":0,"attempts":0}],"background":"","id":"XTehdXO18VOQnQH3RdG0bMpjYQceTbSkI7IuJw1IKmyx","block":"group","name":"Eo3d"},{"text":"(see) their attack.","class":"","id":"8BotE5M696vbjOGP0l8Bxpo6Ex0tNxBWUzJ5dWsMfc1f","block":"text","name":"KdW3"}],"background":"","id":"vuYYOR22","block":"group","name":"9Mks"}],"background":"","id":"C8uY","block":"group","name":"0Tq4"}],"background":"","name":"4Cs6","hidden":false},{"symbol":"FinalizeGroup"}],"id":""}]},"end":{"buttons":{"restart":false},"content":[{"symbol":"finishedAll"}]},"symbols":{"finishedAll":{"class":"w-full","content":[{"block":"group","class":"bg-slate-100 rounded p-5 text-center w-full","content":[{"block":"text","text":"Congratulations, you finished the activity.","class":"","name":"Congra"}],"background":"","name":"CongraGroup"},{"block":"group","class":"text-center p-5","content":[{"block":"finished","name":"finishedBlock"}],"background":"","name":"finishedGroup"}],"background":"","block":"group"},"FinalizeGroup":{"block":"group","class":"text-center mt-10","content":[{"block":"button","class":"mx-auto","to":"/end","text":"Finalize","name":"FinalizeBTN"}],"background":""}}}