{"title":"Practice meaning","clock":true,"countdown":0,"attempts":0,"intro":{"buttons":{"start":"Start"},"content":[]},"activity":{"scenes":[{"block":"scene","name":"SC1","countdown":0,"instructions":{"open":true,"content":[{"block":"group","class":"flex gap-2 items-center","content":[{"block":"audio","class":"","file":"files/INS.mp3","wave":false,"autoplay":false,"id":"","name":"rwfG"},{"block":"text","class":"","text":"Complete the sentences with the words from the boxes, drag the verb that best  completes each sentence,  remember to form <b>FUTURE with PRESENT CONTINIOUS</b>.","id":"","name":"fO6e"}]}]},"content":[{"marker":"📒","class":"bg-sky-400 rounded p-2 max-w-5xl  mx-auto rounded-lg","content":[{"marker":"","class":"max-w-4xl  mx-auto","content":[{"marker":"","class":"grid grid-cols-5 p-5 gap-5 border-4 border-sky-900 rounded-lg bg-sky-300 text-black","content":[{"evaluation":"auto","positiveid":"10","id":"YPXu","class":"bg-transparent ","classitem":"!min-h-[20px] bg-yellow-400 rounded-lg text-center p-1 shadow-md","content":[{"text":"watching","class":"","id":"ufDW","block":"text","name":"4W83"}],"block":"dragitem","name":"pAoP"},{"evaluation":"auto","positiveid":"9","id":"tiAxCdv5","class":"bg-transparent !min-h-[40px]","classitem":"!min-h-[20px] bg-yellow-400 rounded-lg text-center p-1 shadow-md","content":[{"text":"staying","class":"","id":"ufDWT3Ec","block":"text","name":"7c9c"}],"block":"dragitem","name":"1435"},{"evaluation":"auto","positiveid":"2","id":"CO2cpuqO","class":"bg-transparent","classitem":"!min-h-[20px] bg-yellow-400 rounded-lg text-center p-1 shadow-md","content":[{"text":"are having","class":"","id":"ufDWTcpn","block":"text","name":"g936"}],"block":"dragitem","name":"TKNl"},{"evaluation":"auto","positiveid":"1","id":"bNoUCQKZ","class":"bg-transparent","classitem":"!min-h-[20px] bg-yellow-400 rounded-lg text-center p-1 shadow-md","content":[{"text":"studying","class":"","id":"ufDW72GB","block":"text","name":"iMXe"}],"block":"dragitem","name":"2ZrP"},{"evaluation":"auto","positiveid":"6","id":"PVna8X67","class":"bg-transparent","classitem":"!min-h-[20px] bg-yellow-400 rounded-lg text-center p-1 shadow-md","content":[{"text":"Are the kids","class":"","id":"ufDWbOat","block":"text","name":"8iv0"}],"block":"dragitem","name":"OSaw"},{"evaluation":"auto","positiveid":"3","id":"zCvZuB4E","class":"bg-transparent","classitem":"!min-h-[20px] bg-yellow-400 rounded-lg text-center p-1 shadow-md","content":[{"text":"driving","class":"","id":"ufDWTg7N","block":"text","name":"of82"}],"block":"dragitem","name":"xMnk"},{"evaluation":"auto","positiveid":"8","id":"pzkYtpb7","class":"bg-transparent","classitem":"!min-h-[20px] bg-yellow-400 rounded-lg text-center p-1 shadow-md","content":[{"text":"working","class":"","id":"ufDWtFwo","block":"text","name":"LRZ8"}],"block":"dragitem","name":"rN3E"},{"evaluation":"auto","positiveid":"7","id":"zPjauKxM","class":"bg-transparent","classitem":"!min-h-[20px] bg-yellow-400 rounded-lg text-center p-1 shadow-md","content":[{"text":"cooking","class":"","id":"ufDWgYrf","block":"text","name":"kXzn"}],"block":"dragitem","name":"AAl8"},{"evaluation":"auto","positiveid":"4","id":"B8BvkV8h","class":"bg-transparent","classitem":"!min-h-[20px] bg-yellow-400 rounded-lg text-center p-1 shadow-md","content":[{"text":"are not attending ","class":"","id":"ufDWgYrfM4ga","block":"text","name":"Rh2X"}],"block":"dragitem","name":"j0L0"},{"evaluation":"auto","positiveid":"5","id":"tLdcPAqI","class":"bg-transparent","classitem":"!min-h-[20px] bg-yellow-400 rounded-lg text-center p-1 shadow-md","content":[{"text":"are arriving","class":"","id":"ufDWgYrfUw6X","block":"text","name":"1qo3"}],"block":"dragitem","name":"vRcT"}],"background":"","id":"J1De","block":"group","name":"7SxO"},{"marker":"","class":"text-xl","content":[{"marker":"","class":"text-blue-900 border-sky-800 border-4 rounded-lg ","content":[{"marker":"","class":"w-8 h-8 rounded-lg shadow-md bg-yellow-400 inline-block  mx-2  align-middle ","content":[{"text":"1.-","class":"r","id":"uKzQ","block":"text","name":"ZsEM"}],"background":"","id":"WDQM","block":"group","name":"b9fs"},{"text":"Next week, Alexa is","class":"","id":"NsX63zUg","block":"text","name":"9vJC"},{"marker":"","class":"inline-block mx-2  align-middle \n","content":[{"id":"1","class":"bg-blue-200 rounded-lg !min-h-[40px]","block":"dragzone","name":"559x"}],"background":"","id":"IKcH","block":"group","name":"dkEu"},{"text":"for her final exams at the library after school .","class":"","id":"hLQyB9oh","block":"text","name":"60bR"}],"background":"","id":"r5Ne","block":"group","name":"hgYn"}],"background":"","id":"Q3Xg","block":"group","name":"DPJS","hidden":false},{"marker":"","class":"text-xl","content":[{"marker":"","class":"text-blue-900 border-sky-800 border-4 rounded-lg ","content":[{"marker":"","class":"w-8 h-8 rounded-lg shadow-md bg-yellow-400 inline-block  mx-2  align-middle ","content":[{"text":"2.-","class":"r","id":"uKzQfbcy","block":"text","name":"nxRR"}],"background":"","id":"WDQMpovV","block":"group","name":"gbAJ"},{"text":"Samuel and Laura","class":"","id":"NsX63zUgS2V4","block":"text","name":"fgIt"},{"marker":"","class":"inline-block mx-2  align-middle\n","content":[{"id":"2","class":"bg-blue-200 rounded-lg !min-h-[40px]","block":"dragzone","name":"gdLW"}],"background":"","id":"IKcHDoZB","block":"group","name":"iSBd"},{"text":"breakfast together before work.","class":"","id":"hLQyB9ohRc4t","block":"text","name":"FmU4"}],"background":"","id":"r5NepYRQ","block":"group","name":"ve79"}],"background":"","id":"xBNw0t3h","block":"group","name":"6PiF"},{"marker":"","class":"text-xl","content":[{"marker":"","class":"text-blue-900 border-sky-900 border-4 rounded-lg ","content":[{"marker":"","class":"w-8 h-8 rounded-lg shadow-md bg-yellow-400 inline-block  mx-2  align-middle","content":[{"text":"3.-","class":"r","id":"uKzQfbcysGI9","block":"text","name":"7kUK"}],"background":"","id":"WDQMpovVENHZ","block":"group","name":"bV5t"},{"text":"Tomorrow, he is","class":"","id":"NsX63zUgS2V4CoJr","block":"text","name":"BNAW"},{"marker":"","class":"inline-block mx-2  align-middle\n","content":[{"id":"3","class":"bg-blue-200 rounded-lg !min-h-[40px]","block":"dragzone","name":"8Mp8"}],"background":"","id":"IKcHDoZBxV3h","block":"group","name":"yn4Z"},{"text":"to the office in heavy traffic.","class":"","id":"hLQyB9ohRc4tJwx1","block":"text","name":"z596"}],"background":"","id":"r5NepYRQB0kG","block":"group","name":"vX7B"}],"background":"","id":"dKONmX3A","block":"group","name":"GMNQ"},{"marker":"","class":"text-xl","content":[{"marker":"","class":"text-blue-900 border-sky-900 border-4 rounded-lg ","content":[{"marker":"","class":"w-8 h-8 rounded-lg shadow-md bg-yellow-400 inline-block  mx-2  align-middle","content":[{"text":"4.-","class":"r","id":"uKzQfbcysGI9NXmL","block":"text","name":"fBtj"}],"background":"","id":"WDQMpovVENHZYR9T","block":"group","name":"5K30"},{"text":"We","class":"","id":"NsX63zUgS2V4CoJrBrN6","block":"text","name":"mpZ7"},{"marker":"","class":"inline-block mx-2  align-middle\n","content":[{"id":"4","class":"bg-blue-200 rounded-lg !min-h-[40px]","block":"dragzone","name":"5snM"}],"background":"","id":"IKcHDoZBxV3hVMHh","block":"group","name":"sRxn"},{"text":"a meeting with our team at 10 AM, however we","class":"","id":"hLQyB9ohRc4tJwx14jYd","block":"text","name":"im3h"},{"marker":"","class":"inline-block mx-2  align-middle\n","content":[{"id":"5","class":"bg-blue-200 rounded-lg !min-h-[40px]","block":"dragzone","name":"dIOA"}],"background":"","id":"o6mLyB23","block":"group","name":"jrkX"},{"text":"early.","class":"","id":"nSOJaIbj","block":"text","name":"8wIv"}],"background":"","id":"r5NepYRQB0kGumz7","block":"group","name":"OD6I"}],"background":"","id":"96rE7vMI","block":"group","name":"7f4S"},{"marker":"","class":"text-xl","content":[{"marker":"","class":"text-blue-900 border-sky-900 border-4 rounded-lg ","content":[{"marker":"","class":"w-8 h-8 rounded-lg shadow-md bg-yellow-400 inline-block  mx-2  align-middle","content":[{"text":"5.-","class":"r","id":"uKzQfbcysGI9NXmLAmV4","block":"text","name":"qwG8"}],"background":"","id":"WDQMpovVENHZYR9T8aA8","block":"group","name":"GmIs"},{"text":"We","class":"","id":"NsX63zUgS2V4CoJrBrN6qTUZ","block":"text","name":"IzNd","hidden":true},{"marker":"","class":"inline-block mx-2  align-middle\n","content":[{"id":"6","class":"bg-blue-200 rounded-lg !min-h-[40px]","block":"dragzone","name":"6N7W"}],"background":"","id":"IKcHDoZBxV3hVMHh5oFN","block":"group","name":"XVVE"},{"text":"playing in the park with their friends?","class":"","id":"hLQyB9ohRc4tJwx14jYdkB50","block":"text","name":"BNJf"}],"background":"","id":"r5NepYRQB0kGumz7pFlj","block":"group","name":"RUvm"}],"background":"","id":"2Ce4RqMh","block":"group","name":"JePO"},{"marker":"","class":"text-xl","content":[{"marker":"","class":"text-blue-900  border-sky-900 border-4 rounded-lg ","content":[{"marker":"","class":"w-8 h-8 rounded-lg shadow-md bg-yellow-400 inline-block  mx-2  align-middle","content":[{"text":"6.-","class":"r","id":"uKzQfbcysGI9NXmLAmV43pUk","block":"text","name":"aN8M"}],"background":"","id":"WDQMpovVENHZYR9T8aA8CW3x","block":"group","name":"iMg6"},{"text":"Is Emma","class":"","id":"NsX63zUgS2V4CoJrBrN6qTUZGXuh","block":"text","name":"n1WN","hidden":false},{"marker":"","class":"inline-block mx-2  align-middle\n","content":[{"id":"7","class":"bg-blue-200 rounded-lg !min-h-[40px]","block":"dragzone","name":"BpPd"}],"background":"","id":"IKcHDoZBxV3hVMHh5oFNfRiQ","block":"group","name":"ru4Z"},{"text":"dinner next week?","class":"","id":"hLQyB9ohRc4tJwx14jYdkB506SJ1","block":"text","name":"jeae"}],"background":"","id":"r5NepYRQB0kGumz7pFljLSul","block":"group","name":"Sl4a"}],"background":"","id":"1jNcMavt","block":"group","name":"77c0"},{"marker":"","class":"text-xl","content":[{"marker":"","class":"text-blue-900 border-sky-900 border-4 rounded-lg","content":[{"marker":"","class":"w-8 h-8 rounded-lg shadow-md bg-yellow-400 inline-block  mx-2  align-middle","content":[{"text":"7.-","class":"r","id":"uKzQfbcysGI9NXmLAmV43pUkD9fa","block":"text","name":"lkQo"}],"background":"","id":"WDQMpovVENHZYR9T8aA8CW3xvAqC","block":"group","name":"PxvC"},{"text":"He is not","class":"","id":"NsX63zUgS2V4CoJrBrN6qTUZGXuhdSZ6","block":"text","name":"849C","hidden":false},{"marker":"","class":"inline-block mx-2  align-middle\n","content":[{"id":"8","class":"bg-blue-200 rounded-lg !min-h-[40px]","block":"dragzone","name":"Mcas"}],"background":"","id":"IKcHDoZBxV3hVMHh5oFNfRiQ17Vz","block":"group","name":"Jt9x"},{"text":"on his laptop to finish homework later, instead, he is finishing the drawings.","class":"","id":"hLQyB9ohRc4tJwx14jYdkB506SJ1fHvH","block":"text","name":"pUSf"}],"background":"","id":"r5NepYRQB0kGumz7pFljLSulLVy2","block":"group","name":"tI1A"}],"background":"","id":"ooLtF02y","block":"group","name":"Gio3"},{"marker":"","class":"text-xl","content":[{"marker":"","class":"text-blue-900 border-sky-900 border-4 rounded-lg ","content":[{"marker":"","class":"w-8 h-8 rounded-lg shadow-md bg-yellow-400 inline-block  mx-2  align-middle","content":[{"text":"8.-","class":"r","id":"uKzQfbcysGI9NXmLAmV43pUkD9fa3lni","block":"text","name":"mg8f"}],"background":"","id":"WDQMpovVENHZYR9T8aA8CW3xvAqC3a93","block":"group","name":"ZPNX"},{"text":"My brother is","class":"","id":"NsX63zUgS2V4CoJrBrN6qTUZGXuhdSZ6Zx9Z","block":"text","name":"eNgi","hidden":false},{"marker":"","class":"inline-block mx-2  align-middle\n","content":[{"id":"9","class":"bg-blue-200 rounded-lg !min-h-[40px]","block":"dragzone","name":"yMzO"}],"background":"","id":"IKcHDoZBxV3hVMHh5oFNfRiQ17VzNgD3","block":"group","name":"4DUO"},{"text":"home the day after tomorrow, but he won't be helping me with my chores.","class":"","id":"hLQyB9ohRc4tJwx14jYdkB506SJ1fHvHNlw7","block":"text","name":"w3Ij"}],"background":"","id":"r5NepYRQB0kGumz7pFljLSulLVy2BKGK","block":"group","name":"JlS2"}],"background":"","id":"oS0iGEHn","block":"group","name":"tJjn"},{"marker":"","class":"text-xl","content":[{"marker":"","class":"text-blue-900 border-sky-900 border-4 rounded-lg ","content":[{"marker":"","class":"w-8 h-8 rounded-lg shadow-md bg-yellow-400 inline-block  mx-2  align-middle","content":[{"text":"9.-","class":"r","id":"uKzQfbcysGI9NXmLAmV43pUkD9fa3lnif0HT","block":"text","name":"ke6I"}],"background":"","id":"WDQMpovVENHZYR9T8aA8CW3xvAqC3a93rP9X","block":"group","name":"Nz05"},{"text":"They are not","class":"","id":"NsX63zUgS2V4CoJrBrN6qTUZGXuhdSZ6Zx9ZKz3J","block":"text","name":"pYK7","hidden":false},{"marker":"","class":"inline-block mx-2  align-middle\n","content":[{"id":"10","class":"bg-blue-200 rounded-lg !min-h-[40px]","block":"dragzone","name":"BLHi"}],"background":"","id":"IKcHDoZBxV3hVMHh5oFNfRiQ17VzNgD3bF6g","block":"group","name":"B5q8"},{"text":"a movie at the cinema tonight instead they are reading the novel.","class":"","id":"hLQyB9ohRc4tJwx14jYdkB506SJ1fHvHNlw7tuqc","block":"text","name":"sISf"}],"background":"","id":"r5NepYRQB0kGumz7pFljLSulLVy2BKGKJUzq","block":"group","name":"otNO"}],"background":"","id":"7Wyzfbbs","block":"group","name":"QlLv"}],"background":"","id":"5aF4Auvh","block":"group","name":"NdLw"}],"background":"","id":"gpo1","block":"group","name":"gpo1"},{"symbol":"FinalizeGroup"}],"id":""}]},"end":{"buttons":{"restart":false},"content":[{"symbol":"finishedAll"}]},"symbols":{"finishedAll":{"class":"w-full","content":[{"block":"group","class":"bg-slate-100 rounded p-5 text-center w-full","content":[{"block":"text","text":"Congratulations, you finished the activity.","class":"","name":"Congra"}],"background":"","name":"CongraGroup"},{"block":"group","class":"text-center p-5","content":[{"block":"finished","name":"finishedBlock"}],"background":"","name":"finishedGroup"}],"background":"","block":"group"},"FinalizeGroup":{"block":"group","class":"text-center mt-10","content":[{"block":"button","class":"mx-auto","to":"/end","text":"Finalize","name":"FinalizeBTN"}],"background":""}}}