{"title":"Reading comprehension exercise","clock":true,"countdown":0,"attempts":0,"intro":{"buttons":{"start":"Start"},"content":[]},"activity":{"scenes":[{"block":"scene","name":"SC1","countdown":0,"instructions":{"open":true,"content":[{"block":"group","class":"flex gap-2 items-center","content":[{"block":"audio","class":"","file":"files/INS.mp3","wave":false,"autoplay":false,"id":"","name":"Q755"},{"block":"text","class":"","text":"Write the answers to the following questions. Use the past perfect and the simple past when possible.","id":"","name":"lhYH"}]}]},"content":[{"block":"group","class":"bg-slate-100 rounded p-3 my-2 max-w-5xl mx-auto","content":[{"marker":"","class":"mask mask-squircle bg-sky-900 flex justify-center my-10 p-2","content":[{"file":"files/Mesa de trabajo 1@2x-100.jpg","class":"w-2/4 mask mask-squircle","id":"HpU3","block":"image","name":"nHib"}],"background":"","id":"GLiU","block":"group","name":"HOsF"},{"marker":"","class":"","content":[{"marker":"","class":" bg-slate-50 p-5 rounded-lg border-sky-900 border-4 text-2xl p-1 my-1","content":[{"marker":"","class":"","content":[{"text":"1. How long had Emily and Ross practiced before the competition?","class":"","id":"Cg4Y","block":"text","name":"8R53"},{"marker":"","class":"","content":[{"case":false,"evaluation":"manual","class":"text-center","positive":"","multiline":true,"placeholder":"-","showResult":false,"id":"R8ZA","block":"textarea","name":"eyoA","maxlength":100,"attempts":0}],"background":"","id":"69Gi","block":"group","name":"rgZo"}],"background":"","id":"1ZS6","block":"group","name":"vjP7"}],"background":"","id":"aXuw","block":"group","name":"ujsc"},{"marker":"","class":" bg-slate-50 p-5 rounded-lg border-sky-900 border-4 text-2xl p-1 my-1","content":[{"marker":"","class":"","content":[{"text":"2. Before that night, who had seen Emily and Ross dance?","class":"","id":"Cg4Yu8Uf","block":"text","name":"z7IS"},{"marker":"","class":"","content":[{"case":false,"evaluation":"manual","class":"text-center","positive":"","multiline":true,"placeholder":"-","showResult":false,"id":"SmDT","block":"textarea","name":"bCBF","maxlength":100,"attempts":0}],"background":"","id":"69GiKcUR","block":"group","name":"UZ8z"}],"background":"","id":"1ZS6wIvg","block":"group","name":"JDTi"}],"background":"","id":"aXuw7rIO","block":"group","name":"UQGE"},{"marker":"","class":" bg-slate-50 p-5 rounded-lg border-sky-900 border-4 text-2xl p-1 my-1","content":[{"marker":"","class":"","content":[{"text":"3. What happened after everyone had danced?","class":"","id":"Cg4YGbel","block":"text","name":"Cues"},{"marker":"","class":"","content":[{"case":false,"evaluation":"manual","class":"text-center","positive":"","multiline":true,"placeholder":"-","showResult":false,"id":"OKyX","block":"textarea","name":"vT9d","maxlength":100,"attempts":0}],"background":"","id":"69GicQRd","block":"group","name":"8WI7"}],"background":"","id":"1ZS697Se","block":"group","name":"pmyF"}],"background":"","id":"aXuwCcGV","block":"group","name":"fCp9"},{"marker":"","class":" bg-slate-50 p-5 rounded-lg border-sky-900 border-4 text-2xl p-1 my-1","content":[{"marker":"","class":"","content":[{"text":"4. What Ross said about practicing?","class":"","id":"Cg4Yg4Q4","block":"text","name":"6LBg"},{"marker":"","class":"","content":[{"case":false,"evaluation":"manual","class":"text-center","positive":"","multiline":true,"placeholder":"-","showResult":false,"id":"Xed2","block":"textarea","name":"KsoR","maxlength":100,"attempts":0}],"background":"","id":"69GicnoD","block":"group","name":"uHET"}],"background":"","id":"1ZS6lrFv","block":"group","name":"ZY8X"}],"background":"","id":"aXuwqDpp","block":"group","name":"J4IB"},{"marker":"","class":" bg-slate-50 p-5 rounded-lg border-sky-900 border-4 text-2xl p-1 my-1","content":[{"marker":"","class":"","content":[{"text":"5. Who were the best dancers of the competition?","class":"","id":"Cg4Y8jO9","block":"text","name":"vDHV"},{"marker":"","class":"","content":[{"case":false,"evaluation":"manual","class":"text-center","positive":"","multiline":true,"placeholder":"-","showResult":false,"id":"hOQD","block":"textarea","name":"Wcvc","maxlength":100,"attempts":0}],"background":"","id":"69GicPsD","block":"group","name":"ChjI"}],"background":"","id":"1ZS62xrm","block":"group","name":"uPpc"}],"background":"","id":"aXuwGx1b","block":"group","name":"rO5Y"}],"background":"","id":"zRU7","block":"group","name":"kQZ6","hidden":false}],"background":"","name":"4Cs6","hidden":false,"marker":"","id":""},{"symbol":"FinalizeGroup"}],"id":""}]},"end":{"buttons":{"restart":false},"content":[{"symbol":"finishedAll"}]},"symbols":{"finishedAll":{"class":"w-full","content":[{"block":"group","class":"bg-slate-100 rounded p-5 text-center w-full","content":[{"block":"text","text":"Congratulations, you finished the activity.","class":"","name":"Congra"}],"background":"","name":"CongraGroup"},{"block":"group","class":"text-center p-5","content":[{"block":"finished","name":"finishedBlock"}],"background":"","name":"finishedGroup"}],"background":"","block":"group"},"FinalizeGroup":{"block":"group","class":"text-center mt-10","content":[{"block":"button","class":"mx-auto","to":"/end","text":"Finalize","name":"FinalizeBTN"}],"background":""}}}