{"title":"Unit 5: Lesson 1, Exercise F","clock":true,"countdown":0,"attempts":0,"intro":{"buttons":{"start":"Start"},"content":[]},"activity":{"scenes":[{"block":"scene","name":"SC1","countdown":0,"instructions":{"open":true,"content":[{"block":"group","class":"flex gap-2 items-center","content":[{"block":"audio","class":"","file":"files/inst.mp3","wave":false,"autoplay":false,"id":"","name":"t7cX"},{"block":"text","class":"","text":"Think about your current and future obligations. Using must, shall, should, have to, and/or their negative forms, write at least 7 important aspects related to them. Write 100 words minimum and 150 maximum.","id":"","name":"ArfK"}]}]},"content":[{"block":"group","class":"bg-slate-100 rounded p-3 my-2 max-w-3xl mx-auto","content":[{"marker":"","class":"flex justify-center my-5","content":[{"file":"files/img01.jpg","class":"mask mask-circle w-3/4","id":"KNyg","block":"image","name":"Ejij"}],"background":"","id":"kgoq","block":"group","name":"hMjH"},{"marker":"","class":"","content":[{"case":false,"evaluation":"manual","class":"","positive":"","multiline":true,"placeholder":"","showResult":false,"id":"CH70","block":"textarea","name":"l86b","maxlength":0,"attempts":0}],"background":"","id":"LYGC","block":"group","name":"dPex"}],"background":"","name":"4Cs6","hidden":false},{"symbol":"FinalizeGroup"}],"id":""}]},"end":{"buttons":{"restart":false},"content":[{"symbol":"finishedAll"}]},"symbols":{"finishedAll":{"class":"w-full","content":[{"block":"group","class":"bg-slate-100 rounded p-5 text-center w-full","content":[{"block":"text","text":"Congratulations, you finished the activity.","class":"","name":"Congra"}],"background":"","name":"CongraGroup"},{"block":"group","class":"text-center p-5","content":[{"block":"finished","name":"finishedBlock"}],"background":"","name":"finishedGroup"}],"background":"","block":"group"},"FinalizeGroup":{"block":"group","class":"text-center mt-10","content":[{"block":"button","class":"mx-auto","to":"/end","text":"Finalize","name":"FinalizeBTN"}],"background":""}}}